{
  "alunos": {
    "gon19": {
      "n": 10,
      "aluno": "José Gonzaga",
      "cpf": "--",
      "nascimento": "--",
      "idade": "--",
      "genero": "--",
      "whatsapp": "--",
      "email": "--",
      "nivel": "--",
      "q1": "--",
      "q2": "--",
      "q3": "--",
      "q4": "--",
      "q5": "--",
      "q6": "--",
      "q7": "--",
      "q8": "--",
      "q9": "--",
      "objetivo": "Hipertrofia",
      "plano": "Presencial 3x",
      "dias": "Seg Qua Sex",
      "horario": "20:00",
      "mensalidade": "R$100,00",
      "matricula": "R$50,00",
      "total": "R$150,00",
      "valor": 100,
      "venc": "13/05/26",
      "status": "Ativo",
      "id": "gon19"
    },
    "carla38": {
      "n": 1,
      "aluno": "Maria Carla Carvalho Santos",
      "cpf": "417.344.068-52",
      "nascimento": "1996-04-22",
      "idade": "30",
      "genero": "Feminino",
      "whatsapp": "(13) 99768-3699",
      "email": "carlacarvalho8362@gmail.com",
      "nivel": "Iniciante",
      "q1": "Sim",
      "q2": "Mais ou menos, preciso melhorar",
      "q3": "6 a 7 horas",
      "q4": "Não",
      "q5": "Barriga, braços e pernas",
      "q6": "Não",
      "q7": "Sim",
      "q8": "Sim",
      "q9": "Vitaminas e ferro norimpurum",
      "objetivo": "Emagrecimento | Saúde | Hipertrofia | Definição Muscular | Condicionamento Físico | Reabilitação Física",
      "plano": "Presencial 3x",
      "dias": "Terça, Quinta, Sexta",
      "horario": "08:00",
      "mensalidade": "R$100,00",
      "matricula": "R$50,00",
      "total": "R$150,00",
      "valor": 100,
      "venc": "06/08/26",
      "status": "Ativo",
      "id": "carla38"
    },
    "vhellem39": {
      "n": 2,
      "aluno": "Hellem Vitória Carvalho dos Santos",
      "cpf": "417.344.078-24",
      "nascimento": "1999-01-11",
      "idade": "27",
      "genero": "Feminino",
      "whatsapp": "(13) 99645-0471",
      "email": "vitoria2018201@gmail.com",
      "nivel": "Iniciante",
      "q1": "Sim",
      "q2": "Normal,preciso aumentar a proteína",
      "q3": "7 horas",
      "q4": "Não",
      "q5": "Braços,barriga, culote e pernas.",
      "q6": "Não",
      "q7": "Sim",
      "q8": "Sim",
      "q9": "Só noripurum.",
      "objetivo": "Definição Muscular | Saúde | Hipertrofia | Condicionamento Físico | Reabilitação Física | Emagrecimento",
      "plano": "Presencial 3x",
      "dias": "Terça, Quinta, Sexta",
      "horario": "08:00",
      "mensalidade": "R$100,00",
      "matricula": "R$50,00",
      "total": "R$150,00",
      "valor": 100,
      "venc": "06/08/26",
      "status": "Ativo",
      "id": "vhellem39"
    },
    "dani36": {
      "n": 1,
      "aluno": "Daniele Vieira Leite",
      "cpf": "--",
      "nascimento": "--",
      "idade": "--",
      "genero": "--",
      "whatsapp": "--",
      "email": "--",
      "nivel": "--",
      "q1": "--",
      "q2": "--",
      "q3": "--",
      "q4": "--",
      "q5": "--",
      "q6": "--",
      "q7": "--",
      "q8": "--",
      "q9": "--",
      "objetivo": "Definição",
      "plano": "Online",
      "dias": "Seg a Sex",
      "horario": "14:00",
      "mensalidade": "R$60,00",
      "matricula": "R$50,00",
      "total": "R$110,00",
      "valor": 60,
      "venc": "13/05/26",
      "status": "Ativo",
      "id": "dani36"
    },
    "tchu37": {
      "aluno": "Tchuco",
      "cpf": "--",
      "nascimento": "--",
      "idade": "--",
      "genero": "--",
      "whatsapp": "--",
      "email": "--",
      "nivel": "--",
      "q1": "--",
      "q2": "--",
      "q3": "--",
      "q4": "--",
      "q5": "--",
      "q6": "--",
      "q7": "--",
      "q8": "--",
      "q9": "--",
      "objetivo": "Condicionamento físico",
      "plano": "Online",
      "dias": "Online",
      "horario": "14:00",
      "mensalidade": "--",
      "matricula": "--",
      "total": "--",
      "valor": "--",
      "venc": "06/04/26",
      "status": "Desativado",
      "id": "tchu37"
    }
  },
  "horarios": {
    "PRESENCIAL": {
      "06h00 🐦": ["adriana20"],
      "07h00 🌙": ["angel02"],
      "08h00 🐢": ["carla38", "vhellem39"],
      "19h00 🌑": ["nicoli25"],
      "20h00 ⭐": ["gon19"]
    },
    "ONLINE": {
      "14h00": ["dani36", "tchu37"]
    }
  }
}
